{
  "id": "3453757",
  "name": "天猫购物车",
  "font_family": "iconfont",
  "css_prefix_text": "icon-",
  "description": "",
  "glyphs": [
    {
      "icon_id": "14732",
      "name": "向下",
      "font_class": "xiangxia",
      "unicode": "e600",
      "unicode_decimal": 58880
    },
    {
      "icon_id": "577377",
      "name": "旺旺",
      "font_class": "wangwang",
      "unicode": "e75c",
      "unicode_decimal": 59228
    },
    {
      "icon_id": "629357",
      "name": "搜索",
      "font_class": "sousuo",
      "unicode": "e651",
      "unicode_decimal": 58961
    }
  ]
}
